convertpath.py
convertpath/__init__.py
convertpath/convertpath.py
convertpath-0.2.5.dist-info/METADATA
convertpath-0.2.5.dist-info/WHEEL
convertpath-0.2.5.dist-info/top_level.txt
convertpath-0.2.5.dist-info/RECORD
