Metadata-Version: 2.1
Name: convertpath
Version: 0.2.5
Summary: Simple Path Convertor
Home-page: https://github.com/ShinyaAkagiI/convertpath
Author: Shinya Akagi
License: PSF
Platform: UNKNOWN
Requires-Dist: pathlib
